CHANGES.txt
COPYING
MANIFEST.in
README.rst
setup.cfg
setup.py
versioneer.py
caucase/__init__.py
caucase/_version.py
caucase/ca.py
caucase/cli.py
caucase/client.py
caucase/exceptions.py
caucase/http.py
caucase/http_wsgibase.py
caucase/http_wsgirequesthandler.py
caucase/storage.py
caucase/test.py
caucase/utils.py
caucase/version.py
caucase/wsgi.py
caucase.egg-info/PKG-INFO
caucase.egg-info/SOURCES.txt
caucase.egg-info/dependency_links.txt
caucase.egg-info/entry_points.txt
caucase.egg-info/requires.txt
caucase.egg-info/top_level.txt
caucase.egg-info/zip-safe