Metadata-Version: 2.4
Name: caucase
Version: 0.9.17
Summary: Certificate Authority.
Home-page: https://lab.nexedi.com/nexedi/caucase
Author: Vincent Pelletier
Author-email: vincent@nexedi.com
License: GPLv3+ with wide exception for FOSS
Keywords: certificate authority
Classifier: Environment :: Console
Classifier: Environment :: Web Environment
Classifier: Intended Audience :: System Administrators
Classifier: Intended Audience :: Information Technology
Classifier: License :: OSI Approved :: GNU General Public License v3 or later (GPLv3+)
Classifier: Topic :: Security :: Cryptography
Classifier: Topic :: System :: Systems Administration :: Authentication/Directory
Classifier: Topic :: Internet :: WWW/HTTP :: WSGI :: Application
License-File: COPYING
Requires-Dist: cryptography>=2.2.1
Requires-Dist: pyOpenSSL>=18.0.0
Requires-Dist: pem>=18.2.0
Requires-Dist: PyJWT
Requires-Dist: ipaddress; python_version < "3"
Dynamic: author
Dynamic: author-email
Dynamic: classifier
Dynamic: description
Dynamic: description-content-type
Dynamic: home-page
Dynamic: keywords
Dynamic: license
Dynamic: license-file
Dynamic: requires-dist
Dynamic: summary
